markdown_dom/__init__.py
markdown_dom/markdown_section.py
markdown_dom/py.typed
markdown_dom-0.2.0.dist-info/METADATA
markdown_dom-0.2.0.dist-info/WHEEL
markdown_dom-0.2.0.dist-info/licenses/LICENSE
markdown_dom-0.2.0.dist-info/RECORD
