Metadata-Version: 2.4
Name: markdown-dom
Version: 0.2.0
Summary: A library for building and rendering markdown.
License: MIT
License-File: LICENSE
Requires-Python: >=3.10
Requires-Dist: pydantic>=2.10.3
Requires-Dist: pytest>=8.3.4
